Metadata-Version: 1.0
Name: distributions-m-h34
Version: 0.2
Summary: Gaussian and binomial distributions
Home-page: UNKNOWN
Author: Mahmoud Hashem
Author-email: mahmoud.hashem34@outlook.com
License: UNKNOWN
Platform: UNKNOWN
